{
 "maps": [
  {
   "mapName": "Default",
   "mapType": "SSX_TYPE_CONSOLE1_DRIVE",
   "pluginId": "nvdr",
   "pluginName": "Console 1 British Class A Output",
   "displayName": "British Class A Drive",
   "displayNameShort": "BCA",
   "modularLatencyInSeconds": 0.003,
   "useModularInputNormalling": true,
   "useModularOutputNormalling": true,
   "collectionId": "SSX_COLLECTION_CONSOLE1_BRITISH_CLASS_A",
   "parameters": [
    {
     "id": 0,
     "name": "Drive",
     "mapsTo": "OUT_Drive",
     "value": 0.0,
     "leadParamValue": 0.0,
     "leadOutcome": "LEAD_OUTCOME_INACTIVE",
     "followSelf": true
    },
    {
     "id": 1,
     "name": "Drive Character",
     "mapsTo": "OUT_Drive_Character",
     "value": 0.5,
     "displayName": "Character",
     "knobMode": "KNOB_MODE_BIPOLAR",
     "leaderParams": [
      {
       "name": "OUT_Drive"
      }
     ]
    }
   ]
  },
  {
   "mapName": "BCANative",
   "pluginId": "nvdr",
   "pluginName": "Console 1 British Class A Output",
   "displayName": "British Class A Drive",
   "modularLatencyInSeconds": 0.003,
   "useModularInputNormalling": true,
   "useModularOutputNormalling": true,
   "parameters": [
    {
     "id": 0,
     "name": "Drive",
     "mapsTo": "OUT_Drive",
     "value": 0.5
    },
    {
     "id": 1,
     "name": "Drive Character",
     "mapsTo": "OUT_Drive_Character",
     "value": 0.5
    }
   ]
  },
  {
   "mapName": "AmpRoomBCADrive",
   "mapType": "SSX_TYPE_AMP_ROOM_MODULE",
   "pluginId": "nvdr",
   "pluginName": "Console 1 British Class A Output",
   "displayName": "British Class A Drive",
   "modularLatencyInSeconds": 0.003,
   "useModularInputNormalling": true,
   "useModularOutputNormalling": true,
   "parameters": [
    {
     "id": 0,
     "name": "Drive",
     "mapsTo": "SUBPLUGIN_Param1",
     "value": 0.5
    },
    {
     "id": 1,
     "name": "Drive Character",
     "mapsTo": "SUBPLUGIN_Param2",
     "value": 0.5
    }
   ]
  },
  {
   "mapName": "BCAModular",
   "mapType": "SSX_TYPE_MODULAR_MODULE",
   "pluginId": "nvdr",
   "pluginName": "Console 1 British Class A Output",
   "displayName": "British Class A Drive",
   "modularLatencyInSeconds": 0.003,
   "useModularInputNormalling": true,
   "useModularOutputNormalling": true,
   "parameters": [
    {
     "id": 0,
     "name": "Drive",
     "mapsTo": "MODULE_Param1",
     "value": 0.5,
     "virtualInput": 0
    },
    {
     "id": 1,
     "name": "Drive Character",
     "mapsTo": "MODULE_Param2",
     "value": 0.5,
     "virtualInput": 1
    }
   ]
  }
 ]
}
